coreplus/__init__.py
coreplus/configs.py
coreplus/urls.py
coreplus/version.py
coreplus/admin/README.md
coreplus/admin/__init__.py
coreplus/admin/apps.py
coreplus/admin/base.py
coreplus/admin/filters.py
coreplus/admin/mixins.py
coreplus/admin/sites.py
coreplus/admin/locale/id/LC_MESSAGES/django.mo
coreplus/admin/locale/id/LC_MESSAGES/django.po
coreplus/admin/static/coreplus_admin/js/alpine.min.js
coreplus/admin/static/coreplus_admin/js/htmx.min.js
coreplus/admin/static/coreplus_admin/js/jquery.min.js
coreplus/admin/templates/admin/base.html
coreplus/admin/templates/admin/confirmation.html
coreplus/admin/templates/admin/form_view.html
coreplus/admin/templates/admin/inspect.html
coreplus/admin/templates/admin/inspect_object_tools.html
coreplus/admin/templates/admin/object_buttons.html
coreplus/admin/templates/admin/print.html
coreplus/admin/templates/admin/print_cover.html
coreplus/admin/templates/admin/print_footer.html
coreplus/admin/templates/admin/print_header.html
coreplus/ads/__init__.py
coreplus/ads/tests.py
coreplus/ads/api/__init__.py
coreplus/ads/api/v1/__init__.py
coreplus/ads/api/v1/tests.py
coreplus/ads/api/v1/urls.py
coreplus/api/README.md
coreplus/api/__init__.py
coreplus/api/apps.py
coreplus/api/consts.py
coreplus/api/helpers.py
coreplus/api/schemas.py
coreplus/api/urls.py
coreplus/api/views.py
coreplus/api/endpoints/__init__.py
coreplus/api/endpoints/serializers.py
coreplus/api/endpoints/v1.py
coreplus/api/endpoints/v2.py
coreplus/api/locale/id/LC_MESSAGES/django.mo
coreplus/api/locale/id/LC_MESSAGES/django.po
coreplus/api/templates/drf_spectacular/redoc.html
coreplus/contacts/__init__.py
coreplus/contacts/abstracts.py
coreplus/contacts/admin.py
coreplus/contacts/apps.py
coreplus/contacts/gis.py
coreplus/contacts/inlines.py
coreplus/contacts/models.py
coreplus/contacts/api/__init__.py
coreplus/contacts/api/v1/__init__.py
coreplus/contacts/api/v1/serializers.py
coreplus/contacts/locale/id/LC_MESSAGES/django.mo
django_coreplus-0.4.dist-info/LICENSE
django_coreplus-0.4.dist-info/METADATA
django_coreplus-0.4.dist-info/WHEEL
django_coreplus-0.4.dist-info/top_level.txt
django_coreplus-0.4.dist-info/RECORD
