Metadata-Version: 2.1
Name: django-coreplus
Version: 0.4
Summary: Django functional modules
Home-page: https://gitlab.com/zeroplus/django/django-coreplus
Author: Zero Plus
Author-email: sasri.works@gmail.com
License: MIT
Project-URL: Documentation, https://gitlab.com/zeroplus/django/django-coreplus/-/wikis/
Project-URL: Source, https://gitlab.com/zeroplus/django/django-coreplus
Classifier: Environment :: Web Environment
Classifier: Framework :: Django
Classifier: Intended Audience :: Developers
Classifier: License :: OSI Approved :: MIT License
Classifier: Operating System :: OS Independent
Classifier: Programming Language :: Python
Classifier: Programming Language :: Python :: 3
Classifier: Programming Language :: Python :: 3 :: Only
Classifier: Programming Language :: Python :: 3.8
Classifier: Programming Language :: Python :: 3.9
Classifier: Topic :: Internet :: WWW/HTTP
Classifier: Topic :: Internet :: WWW/HTTP :: Dynamic Content
Classifier: Topic :: Internet :: WWW/HTTP :: WSGI
Classifier: Topic :: Software Development :: Libraries :: Python Modules
Classifier: Topic :: Software Development :: Libraries :: Application Frameworks
Requires-Python: >=3.8
License-File: LICENSE
Requires-Dist: django (<=4.2.3,>=3.2.8)
Requires-Dist: django-taggit
Requires-Dist: django-import-export
Requires-Dist: django-tinymce
Requires-Dist: django-widget-tweaks
Requires-Dist: django-wkhtmltopdf
Requires-Dist: django-haystack[elasticsearch]
Requires-Dist: django-notifications-hq
Requires-Dist: django-phonenumber-field
Requires-Dist: django-polymorphic
Requires-Dist: django-push-notifications
Requires-Dist: django-filter
Requires-Dist: django-filer (<=2.2.3)
Requires-Dist: drf-spectacular
Requires-Dist: drf-spectacular-sidecar
Requires-Dist: langdetect
Requires-Dist: easy-thumbnails
Requires-Dist: babel
Requires-Dist: bleach
Requires-Dist: boto3
Requires-Dist: mistune (<=2.0.4)
Requires-Dist: scikit-learn
Requires-Dist: phonenumbers
Requires-Dist: pillow
Requires-Dist: pycountry
Requires-Dist: qrcode
Requires-Dist: whoosh
Requires-Dist: geopy
